marktest/__init__.py
marktest/helloworld.py
marktest-1.0.3.dist-info/METADATA
marktest-1.0.3.dist-info/WHEEL
marktest-1.0.3.dist-info/top_level.txt
marktest-1.0.3.dist-info/RECORD
