Metadata-Version: 2.1
Name: marktest
Version: 1.0.3
Summary: Een test pippackage voor project
Home-page: UNKNOWN
Author: Mark Rozing
Author-email: markrozing@hotmail.nl
License: MIT
Keywords: test
Platform: UNKNOWN
